cobwood/__init__.py
cobwood/faostat_legacy.py
cobwood/gfpmx.py
cobwood/gfpmx_data.py
cobwood/gfpmx_equations.py
cobwood/gfpmx_plot.py
cobwood/gfpmx_qaqc.py
cobwood/gfpmx_spreadsheet_to_csv.py
cobwood/logger.py
cobwood/scenario.py
cobwood/eurostat/population.py
cobwood/faostat/__init__.py
cobwood/tests/test_gfpmx_equations.py
cobwood-0.2.1.dist-info/licenses/Licence.txt
cobwood-0.2.1.dist-info/METADATA
cobwood-0.2.1.dist-info/WHEEL
cobwood-0.2.1.dist-info/top_level.txt
cobwood-0.2.1.dist-info/RECORD
