Metadata-Version: 2.4
Name: cobwood
Version: 0.2.1
Summary: Python package that implements a Cobweb version of the Global Forest Trade Model
Author-email: Paul Rougieux <paul.rougieux@ec.europa.eu>, Sarah Mubareka <sarah.mubareka@ec.europa.eu>
Maintainer-email: Sarah Mubareka <sarah.mubareka@ec.europa.eu>, Selene Patani <selene.patani@ext.ec.europa.eu>
License-Expression: MIT
Project-URL: Homepage, https://gitlab.com/bioeconomy/cobwood/cobwood
Project-URL: Bug Reports, https://gitlab.com/bioeconomy/cobwood/cobwood/-/issues
Project-URL: Source, https://gitlab.com/bioeconomy/cobwood/cobwood
Keywords: cobweb,global forest sector,GFPMX,modeling
Classifier: Development Status :: 4 - Beta
Classifier: Intended Audience :: Science/Research
Classifier: Topic :: Scientific/Engineering
Classifier: Programming Language :: Python :: 3
Requires-Python: >=3.8
License-File: Licence.txt
Requires-Dist: PyYAML
Requires-Dist: netCDF4
Requires-Dist: numpy
Requires-Dist: pandas
Requires-Dist: pyxlsb
Requires-Dist: seaborn
Requires-Dist: tqdm
Requires-Dist: xarray
Provides-Extra: notebooks
Requires-Dist: matplotlib; extra == "notebooks"
Requires-Dist: biotrade; extra == "notebooks"
Provides-Extra: dev
Requires-Dist: pytest; extra == "dev"
Dynamic: license-file
